hello_world/__init__.py
hello_world/hello_world.py
hello_world/location.py
tests/__init__.py
tests/test_hello_world.py
tests/test_location.py
hello_world_python-0.0.4.dist-info/METADATA
hello_world_python-0.0.4.dist-info/WHEEL
hello_world_python-0.0.4.dist-info/top_level.txt
hello_world_python-0.0.4.dist-info/RECORD
