Metadata-Version: 2.1
Name: hello-world-python
Version: 0.0.4
Summary: Test github actions
Home-page: https://github.com/garimaarorashuttl/hello-world-python.git
Author: garimaarora
Author-email: garimaarora786@gmail.com
License: MIT
Platform: UNKNOWN
Classifier: Programming Language :: Python :: 3.7
Requires-Dist: shapely
Requires-Dist: pytz
Provides-Extra: dev
Requires-Dist: flake8 ; extra == 'dev'
Provides-Extra: test
Requires-Dist: pytest ; extra == 'test'
Requires-Dist: pytest-runner ; extra == 'test'
Requires-Dist: pytest-cov ; extra == 'test'
Requires-Dist: pytest-pep8 ; extra == 'test'
